<?xml version="1.0" encoding="UTF-8"?><wowhead><item id="23125"><name><![CDATA[Chains of the Lich]]></name><level>60</level><quality id="3">Rare</quality><class id="4"><![CDATA[Armor]]></class><subclass id="-3"><![CDATA[Amulets]]></subclass><icon displayId="18172">inv_belt_18</icon><inventorySlot id="2">Neck</inventorySlot><htmlTooltip><![CDATA[<table><tr><td><!--nstart--><b class="q3">Chains of the Lich</b><!--nend--><!--ndstart--><!--ndend--><span class="q"><br>Item Level <!--ilvl-->60</span><br /><!--bo-->Binds when picked up<table width="100%"><tr><td>Neck</td><th><!--scstart4:-3--><span class="q1"></span><!--scend--></th></tr></table><!--ebstats--><!--egstats--><!--eistats--><!--e--><!--ps--></td></tr></table><table><tr><td>Requires Level <!--rlvl-->55<br><span class="q2">Equip: <a href="https://classic.wowhead.com/spell=15714" class="q2">Increases damage and healing done by magical spells and effects by up to 22.</a></span><!--itemEffects:1--><div class="whtt-sellprice">Sell Price: <span class="moneygold">4</span> <span class="moneysilver">19</span> <span class="moneycopper">53</span></div><div class="whtt-extra whtt-droppedby">Dropped by: Balzaphon</div></td></tr></table>]]></htmlTooltip><json><![CDATA["armor":0,"classs":4,"displayid":18172,"flags2":8192,"id":23125,"level":60,"name":"Chains of the Lich","quality":3,"reqlevel":55,"slot":2,"slotbak":2,"source":[2],"sourcemore":[{"n":"Balzaphon","t":1,"ti":14684}],"subclass":-3]]></json><jsonEquip><![CDATA["displayid":18172,"dmgrange":1.00,"reqlevel":55,"sellprice":41953,"slotbak":2,"splpwr":22]]></jsonEquip><link>https://classic.wowhead.com/item=23125</link></item></wowhead>