<?xml version="1.0" encoding="UTF-8"?><wowhead><item id="10019"><name><![CDATA[Dreamweave Gloves]]></name><level>45</level><quality id="3">Rare</quality><class id="4"><![CDATA[Armor]]></class><subclass id="1"><![CDATA[Cloth Armor]]></subclass><icon displayId="18999">inv_gauntlets_18</icon><inventorySlot id="10">Hands</inventorySlot><htmlTooltip><![CDATA[<table><tr><td><!--nstart--><b class="q3">Dreamweave Gloves</b><!--nend--><!--ndstart--><!--ndend--><span class="q"><br>Item Level <!--ilvl-->45</span><br /><!--bo-->Binds when equipped<table width="100%"><tr><td>Hands</td><th><!--scstart4:1--><span class="q1">Cloth</span><!--scend--></th></tr></table><span><!--amr-->41 Armor</span><br><span><!--stat5-->+4 Intellect</span><br><span><!--stat6-->+7 Spirit</span><!--ebstats--><!--egstats--><!--eistats--><!--e--><!--ps--><br>Durability 30 / 30</td></tr></table><table><tr><td>Requires Level <!--rlvl-->40<br><span class="q2">Equip: <a href="https://classic.wowhead.com/spell=9346" class="q2">Increases damage and healing done by magical spells and effects by up to 18.</a></span><!--itemEffects:1--><div class="whtt-sellprice">Sell Price: <span class="moneysilver">39</span> <span class="moneycopper">44</span></div></td></tr></table>]]></htmlTooltip><json><![CDATA["armor":41,"classs":4,"displayid":18999,"flags2":8192,"id":10019,"level":45,"name":"Dreamweave Gloves","quality":3,"reqlevel":40,"slot":10,"slotbak":10,"source":[1],"sourcemore":[{"c":11,"icon":"inv_gauntlets_18","n":"Dreamweave Gloves","s":197,"t":6,"ti":12067}],"subclass":1]]></json><jsonEquip><![CDATA["armor":41,"avgbuyout":51969,"displayid":18999,"dmgrange":1.00,"dura":30,"int":4,"reqlevel":40,"sellprice":3944,"slotbak":10,"spi":7,"splpwr":18]]></jsonEquip><createdBy><spell id="12067" name="Dreamweave Gloves" icon="inv_gauntlets_18" minCount="0" maxCount="0"><reagent id="4339" name="Bolt of Mageweave" quality="1" icon="inv_fabric_mageweave_03" count="4" /><reagent id="8153" name="Wildvine" quality="1" icon="inv_misc_herb_03" count="4" /><reagent id="10286" name="Heart of the Wild" quality="1" icon="inv_misc_herb_08" count="2" /><reagent id="8343" name="Heavy Silken Thread" quality="1" icon="inv_fabric_silk_02" count="2" /></spell></createdBy><link>https://classic.wowhead.com/item=10019</link></item></wowhead>