<?xml version="1.0" encoding="UTF-8"?><wowhead><item id="22961"><name><![CDATA[Band of Reanimation]]></name><level>83</level><quality id="4">Epic</quality><class id="4"><![CDATA[Armor]]></class><subclass id="-2"><![CDATA[Rings]]></subclass><icon displayId="35367">inv_jewelry_ring_49naxxramas</icon><inventorySlot id="11">Finger</inventorySlot><htmlTooltip><![CDATA[<table><tr><td><!--nstart--><b class="q4">Band of Reanimation</b><!--nend--><!--ndstart--><!--ndend--><span class="q"><br>Item Level <!--ilvl-->83</span><br /><!--bo-->Binds when picked up<br />Unique<table width="100%"><tr><td>Finger</td><th><!--scstart4:-2--><span class="q1"></span><!--scend--></th></tr></table><span><!--stat3-->+34 Agility</span><!--ebstats--><!--egstats--><!--eistats--><!--e--><!--ps--></td></tr></table><table><tr><td>Requires Level <!--rlvl-->60<!--itemEffects:1--><div class="whtt-sellprice">Sell Price: <span class="moneygold">11</span> <span class="moneysilver">36</span> <span class="moneycopper">42</span></div><div class="whtt-extra whtt-droppedby">Dropped by: Patchwerk</div></td></tr></table>]]></htmlTooltip><json><![CDATA["armor":0,"classs":4,"displayid":35367,"flags2":8192,"id":22961,"level":83,"name":"Band of Reanimation","quality":4,"reqlevel":60,"slot":11,"slotbak":11,"source":[2],"sourcemore":[{"bd":1,"n":"Patchwerk","t":1,"ti":16028,"z":3456}],"subclass":-2]]></json><jsonEquip><![CDATA["agi":34,"displayid":35367,"dmgrange":1.00,"maxcount":1,"reqlevel":60,"sellprice":113642,"slotbak":11]]></jsonEquip><link>https://classic.wowhead.com/item=22961</link></item></wowhead>