<?xml version="1.0" encoding="UTF-8"?><wowhead><item id="1998"><name><![CDATA[Bloodscalp Channeling Staff]]></name><level>33</level><quality id="2">Uncommon</quality><class id="2"><![CDATA[Weapons]]></class><subclass id="10"><![CDATA[Staves]]></subclass><icon displayId="20356">inv_staff_18</icon><inventorySlot id="17">Two-Hand</inventorySlot><htmlTooltip><![CDATA[<table><tr><td><!--nstart--><b class="q2">Bloodscalp Channeling Staff</b><!--nend--><!--ndstart--><!--ndend--><span class="q"><br>Item Level <!--ilvl-->33</span><br /><!--bo-->Binds when equipped<table width="100%"><tr><td>Two-Hand</td><th><!--scstart2:10--><span class="q1">Staff</span><!--scend--></th></tr></table><table width="100%"><tr>
    <td><span><!--dmg-->50 - 75 Damage</span></td>
    <th>Speed <!--spd-->2.80</th>
</tr></table><!--dps-->(22.32 damage per second)<!--ebstats--><!--egstats--><!--eistats--><!--e--><!--ps--><br>Durability 85 / 85</td></tr></table><table><tr><td>Requires Level <!--rlvl-->28<br><span class="q2">Equip: <a href="https://classic.wowhead.com/spell=9359" class="q2">Increases damage done by Nature spells and effects by up to 19.</a></span><!--itemEffects:1--><div class="whtt-sellprice">Sell Price: <span class="moneysilver">72</span> <span class="moneycopper">39</span></div><div class="whtt-extra whtt-droppedby">Dropped by: Bloodscalp Shaman</div><div class="whtt-extra whtt-dropchance">Drop Chance: 0.76%</div></td></tr></table>]]></htmlTooltip><json><![CDATA["classs":2,"displayid":20356,"dps":22.32,"flags2":8192,"id":1998,"level":33,"name":"Bloodscalp Channeling Staff","quality":2,"reqlevel":28,"slot":17,"slotbak":17,"source":[2],"sourcemore":[{"n":"Bloodscalp Shaman","t":1,"ti":697,"z":33}],"speed":2.80,"subclass":10]]></json><jsonEquip><![CDATA["avgbuyout":5900,"displayid":20356,"dmgmax1":75,"dmgmin1":50,"dmgrange":1.00,"dmgtype1":0,"dps":22.32,"dura":85,"mledmgmax":75,"mledmgmin":50,"mledps":22.32,"mlespeed":2.80,"natsplpwr":19,"reqlevel":28,"sellprice":7239,"sheathtype":2,"slotbak":17,"speed":2.80]]></jsonEquip><link>https://classic.wowhead.com/item=1998</link></item></wowhead>