<?xml version="1.0" encoding="UTF-8"?><wowhead><item id="9934"><name><![CDATA[Brigade Pauldrons]]></name><level>44</level><quality id="2">Uncommon</quality><class id="4"><![CDATA[Armor]]></class><subclass id="3"><![CDATA[Mail Armor]]></subclass><icon displayId="25935">inv_shoulder_23</icon><inventorySlot id="3">Shoulder</inventorySlot><htmlTooltip><![CDATA[<table><tr><td><!--nstart--><b class="q2">Brigade Pauldrons</b><!--nend--><!--ndstart--><!--ndend--><span class="q"><br>Item Level <!--ilvl-->44</span><br /><!--bo-->Binds when equipped<table width="100%"><tr><td>Shoulder</td><th><!--scstart4:3--><span class="q1">Mail</span><!--scend--></th></tr></table><span><!--amr-->184 Armor</span><br><!--re--><span class="q2">&lt;Random enchantment&gt;</span><!--ebstats--><!--egstats--><!--eistats--><!--e--><!--ps--><br>Durability 60 / 60</td></tr></table><table><tr><td>Requires Level <!--rlvl-->39<!--itemEffects:1--><div class="whtt-sellprice">Sell Price: <span class="moneysilver">65</span> <span class="moneycopper">77</span></div></td></tr></table>]]></htmlTooltip><json><![CDATA["armor":184,"classs":4,"displayid":25935,"flags2":8192,"id":9934,"level":44,"name":"Brigade Pauldrons","quality":2,"reqlevel":39,"slot":3,"slotbak":3,"source":[2],"subclass":3]]></json><jsonEquip><![CDATA["armor":184,"avgbuyout":13999,"displayid":25935,"dmgrange":1.00,"dura":60,"reqlevel":39,"sellprice":6577,"slotbak":3]]></jsonEquip><link>https://classic.wowhead.com/item=9934</link></item></wowhead>