<?xml version="1.0" encoding="UTF-8"?><wowhead><item id="14908"><name><![CDATA[Brutish Legguards]]></name><level>48</level><quality id="2">Uncommon</quality><class id="4"><![CDATA[Armor]]></class><subclass id="4"><![CDATA[Plate Armor]]></subclass><icon displayId="27900">inv_pants_04</icon><inventorySlot id="7">Legs</inventorySlot><htmlTooltip><![CDATA[<table><tr><td><!--nstart--><b class="q2">Brutish Legguards</b><!--nend--><!--ndstart--><!--ndend--><span class="q"><br>Item Level <!--ilvl-->48</span><br /><!--bo-->Binds when equipped<table width="100%"><tr><td>Legs</td><th><!--scstart4:4--><span class="q1">Plate</span><!--scend--></th></tr></table><span><!--amr-->405 Armor</span><br><!--re--><span class="q2">&lt;Random enchantment&gt;</span><!--ebstats--><!--egstats--><!--eistats--><!--e--><!--ps--><br>Durability 85 / 85</td></tr></table><table><tr><td>Requires Level <!--rlvl-->43<!--itemEffects:1--><div class="whtt-sellprice">Sell Price: <span class="moneysilver">81</span> <span class="moneycopper">95</span></div></td></tr></table>]]></htmlTooltip><json><![CDATA["armor":405,"classs":4,"displayid":27900,"flags2":8192,"id":14908,"level":48,"name":"Brutish Legguards","quality":2,"reqlevel":43,"slot":7,"slotbak":7,"source":[2],"subclass":4]]></json><jsonEquip><![CDATA["armor":405,"avgbuyout":24221,"displayid":27900,"dmgrange":1.00,"dura":85,"reqlevel":43,"sellprice":8195,"slotbak":7]]></jsonEquip><link>https://classic.wowhead.com/item=14908</link></item></wowhead>