<?xml version="1.0" encoding="UTF-8"?><wowhead><item id="4697"><name><![CDATA[Burnished Girdle]]></name><level>20</level><quality id="2">Uncommon</quality><class id="4"><![CDATA[Armor]]></class><subclass id="3"><![CDATA[Mail Armor]]></subclass><icon displayId="25767">inv_belt_34</icon><inventorySlot id="6">Waist</inventorySlot><htmlTooltip><![CDATA[<table><tr><td><!--nstart--><b class="q2">Burnished Girdle</b><!--nend--><!--ndstart--><!--ndend--><span class="q"><br>Item Level <!--ilvl-->20</span><br /><!--bo-->Binds when equipped<table width="100%"><tr><td>Waist</td><th><!--scstart4:3--><span class="q1">Mail</span><!--scend--></th></tr></table><span><!--amr-->94 Armor</span><br><span><!--stat4-->+4 Strength</span><br><span><!--stat7-->+2 Stamina</span><!--ebstats--><!--egstats--><!--eistats--><!--e--><!--ps--><br>Durability 30 / 30</td></tr></table><table><tr><td>Requires Level <!--rlvl-->15<!--itemEffects:1--><div class="whtt-sellprice">Sell Price: <span class="moneysilver">4</span> <span class="moneycopper">35</span></div></td></tr></table>]]></htmlTooltip><json><![CDATA["armor":94,"classs":4,"displayid":25767,"flags2":8192,"id":4697,"level":20,"name":"Burnished Girdle","quality":2,"reqlevel":15,"slot":6,"slotbak":6,"source":[2],"subclass":3]]></json><jsonEquip><![CDATA["armor":94,"avgbuyout":2405,"displayid":25767,"dmgrange":1.00,"dura":30,"reqlevel":15,"sellprice":435,"slotbak":6,"sta":2,"str":4]]></jsonEquip><link>https://classic.wowhead.com/item=4697</link></item></wowhead>