<?xml version="1.0" encoding="UTF-8"?><wowhead><item id="2912"><name><![CDATA[Claw of the Shadowmancer]]></name><level>32</level><quality id="3">Rare</quality><class id="2"><![CDATA[Weapons]]></class><subclass id="15"><![CDATA[Daggers]]></subclass><icon displayId="20320">inv_weapon_shortblade_16</icon><inventorySlot id="13">One-Hand</inventorySlot><htmlTooltip><![CDATA[<table><tr><td><!--nstart--><b class="q3">Claw of the Shadowmancer</b><!--nend--><!--ndstart--><!--ndend--><span class="q"><br>Item Level <!--ilvl-->32</span><br /><!--bo-->Binds when equipped<br />Unique<table width="100%"><tr><td>One-Hand</td><th><!--scstart2:15--><span class="q1">Dagger</span><!--scend--></th></tr></table><table width="100%"><tr>
    <td><span><!--dmg-->27 - 51 Damage</span></td>
    <th>Speed <!--spd-->1.90</th>
</tr></table><!--dps-->(20.53 damage per second)<br><span><!--stat5-->+2 Intellect</span><!--ebstats--><!--egstats--><!--eistats--><!--e--><!--ps--><br>Durability 65 / 65</td></tr></table><table><tr><td>Requires Level <!--rlvl-->27<br><span class="q2">Chance on hit: <a href="https://classic.wowhead.com/spell=16409" class="q2">Sends a shadowy bolt at the enemy causing 35 Shadow damage.</a></span><!--itemEffects:1--><div class="whtt-sellprice">Sell Price: <span class="moneysilver">67</span> <span class="moneycopper">31</span></div></td></tr></table>]]></htmlTooltip><json><![CDATA["classs":2,"displayid":20320,"dps":20.53,"flags2":8192,"id":2912,"level":32,"name":"Claw of the Shadowmancer","quality":3,"reqlevel":27,"slot":13,"slotbak":13,"source":[2],"speed":1.90,"subclass":15]]></json><jsonEquip><![CDATA["avgbuyout":55000,"displayid":20320,"dmgmax1":51,"dmgmin1":27,"dmgrange":1.00,"dmgtype1":0,"dps":20.53,"dura":65,"int":2,"maxcount":1,"mledmgmax":51,"mledmgmin":27,"mledps":20.53,"mlespeed":1.90,"reqlevel":27,"sellprice":6731,"sheathtype":3,"slotbak":13,"speed":1.90]]></jsonEquip><link>https://classic.wowhead.com/item=2912</link></item></wowhead>