<?xml version="1.0" encoding="UTF-8"?><wowhead><item id="18282"><name><![CDATA[Core Marksman Rifle]]></name><level>65</level><quality id="4">Epic</quality><class id="2"><![CDATA[Weapons]]></class><subclass id="3"><![CDATA[Guns]]></subclass><icon displayId="31210">inv_weapon_rifle_05</icon><inventorySlot id="15">Ranged</inventorySlot><htmlTooltip><![CDATA[<table><tr><td><!--nstart--><b class="q4">Core Marksman Rifle</b><!--nend--><!--ndstart--><!--ndend--><span class="q"><br>Item Level <!--ilvl-->65</span><br /><!--bo-->Binds when equipped<table width="100%"><tr><td>Ranged</td><th><!--scstart2:3--><span class="q1">Gun</span><!--scend--></th></tr></table><table width="100%"><tr>
    <td><span><!--dmg-->64 - 120 Damage</span></td>
    <th>Speed <!--spd-->2.50</th>
</tr></table><!--dps-->(36.80 damage per second)<!--ebstats--><!--egstats--><!--eistats--><!--e--><!--ps--><br>Durability 90 / 90</td></tr></table><table><tr><td>Requires Level <!--rlvl-->60<br><span class="q2">Equip: <a href="https://classic.wowhead.com/spell=21434" class="q2">+22 ranged Attack Power.</a></span><br><span class="q2">Equip: <a href="https://classic.wowhead.com/spell=15464" class="q2">Improves your chance to hit by 1%.</a></span><!--itemEffects:1--><div class="whtt-sellprice">Sell Price: <span class="moneygold">6</span> <span class="moneysilver">63</span> <span class="moneycopper">47</span></div></td></tr></table>]]></htmlTooltip><json><![CDATA["classs":2,"displayid":31210,"dps":36.80,"flags2":8192,"id":18282,"level":65,"name":"Core Marksman Rifle","quality":4,"reqlevel":60,"slot":15,"slotbak":26,"source":[1],"sourcemore":[{"c":11,"icon":"inv_weapon_rifle_05","n":"Core Marksman Rifle","s":202,"t":6,"ti":22795}],"speed":2.50,"subclass":3]]></json><jsonEquip><![CDATA["avgbuyout":6250000,"displayid":31210,"dmgmax1":120,"dmgmin1":64,"dmgrange":1.00,"dmgtype1":3,"dps":36.80,"dura":90,"mlehitpct":1,"reqlevel":60,"rgdatkpwr":22,"rgddmgmax":120,"rgddmgmin":64,"rgddps":36.80,"rgdhitpct":1,"rgdspeed":2.50,"sellprice":66347,"slotbak":26,"speed":2.50]]></jsonEquip><createdBy><spell id="22795" name="Core Marksman Rifle" icon="inv_weapon_rifle_05" minCount="0" maxCount="0"><reagent id="17010" name="Fiery Core" quality="3" icon="spell_fire_flamebolt" count="4" /><reagent id="17011" name="Lava Core" quality="3" icon="spell_nature_earthquake" count="2" /><reagent id="12360" name="Arcanite Bar" quality="2" icon="inv_misc_stonetablet_05" count="6" /><reagent id="16006" name="Delicate Arcanite Converter" quality="1" icon="inv_gizmo_07" count="2" /><reagent id="16000" name="Thorium Tube" quality="1" icon="inv_gizmo_pipe_04" count="2" /></spell></createdBy><link>https://classic.wowhead.com/item=18282</link></item></wowhead>