<?xml version="1.0" encoding="UTF-8"?><wowhead><item id="22938"><name><![CDATA[Cryptfiend Silk Cloak]]></name><level>83</level><quality id="4">Epic</quality><class id="4"><![CDATA[Armor]]></class><subclass id="-6"><![CDATA[Cloaks]]></subclass><icon displayId="35312">inv_misc_cape_naxxramas_02</icon><inventorySlot id="16">Back</inventorySlot><htmlTooltip><![CDATA[<table><tr><td><!--nstart--><b class="q4">Cryptfiend Silk Cloak</b><!--nend--><!--ndstart--><!--ndend--><span class="q"><br>Item Level <!--ilvl-->83</span><br /><!--bo-->Binds when picked up<table width="100%"><tr><td>Back</td></table><span><!--amr-->203 Armor</span><br><span><!--stat7-->+14 Stamina</span><!--ebstats--><!--egstats--><!--eistats--><!--e--><!--ps--></td></tr></table><table><tr><td>Requires Level <!--rlvl-->60<br><span class="q2">Equip: <a href="https://classic.wowhead.com/spell=13385" class="q2">Increased Defense +7.</a></span><br><span class="q2">Equip: <a href="https://classic.wowhead.com/spell=13669" class="q2">Increases your chance to dodge an attack by 1%.</a></span><br><span class="q2">Equip: <a href="https://classic.wowhead.com/spell=15464" class="q2">Improves your chance to hit by 1%.</a></span><!--itemEffects:1--><div class="whtt-sellprice">Sell Price: <span class="moneygold">6</span> <span class="moneysilver">16</span> <span class="moneycopper">51</span></div><div class="whtt-extra whtt-droppedby">Dropped by: Anub'Rekhan</div></td></tr></table>]]></htmlTooltip><json><![CDATA["armor":203,"classs":4,"displayid":35312,"flags2":8192,"id":22938,"level":83,"name":"Cryptfiend Silk Cloak","quality":4,"reqlevel":60,"slot":16,"slotbak":16,"source":[2],"sourcemore":[{"bd":1,"n":"Anub'Rekhan","t":1,"ti":15956,"z":3456}],"subclass":-6]]></json><jsonEquip><![CDATA["armor":203,"def":7,"displayid":35312,"dmgrange":1.00,"dodgepct":1,"mlehitpct":1,"reqlevel":60,"rgdhitpct":1,"sellprice":61651,"slotbak":16,"sta":14]]></jsonEquip><link>https://classic.wowhead.com/item=22938</link></item></wowhead>