<?xml version="1.0" encoding="UTF-8"?><wowhead><item id="6572"><name><![CDATA[Defender Shield]]></name><level>23</level><quality id="2">Uncommon</quality><class id="4"><![CDATA[Armor]]></class><subclass id="6"><![CDATA[Shields]]></subclass><icon displayId="18701">inv_shield_06</icon><inventorySlot id="14">Shield</inventorySlot><htmlTooltip><![CDATA[<table><tr><td><!--nstart--><b class="q2">Defender Shield</b><!--nend--><!--ndstart--><!--ndend--><span class="q"><br>Item Level <!--ilvl-->23</span><br /><!--bo-->Binds when equipped<table width="100%"><tr><td>Off Hand</td><th><!--scstart4:6--><span class="q1">Shield</span><!--scend--></th></tr></table><span><!--amr-->461 Armor</span><br>8 Block<br><!--re--><span class="q2">&lt;Random enchantment&gt;</span><!--ebstats--><!--egstats--><!--eistats--><!--e--><!--ps--><br>Durability 70 / 70</td></tr></table><table><tr><td>Requires Level <!--rlvl-->18<!--itemEffects:1--><div class="whtt-sellprice">Sell Price: <span class="moneysilver">13</span> <span class="moneycopper">23</span></div></td></tr></table>]]></htmlTooltip><json><![CDATA["armor":461,"classs":4,"displayid":18701,"flags2":8192,"id":6572,"level":23,"name":"Defender Shield","quality":2,"reqlevel":18,"slot":14,"slotbak":14,"source":[2],"subclass":6]]></json><jsonEquip><![CDATA["armor":461,"avgbuyout":3969,"blockamount":8,"displayid":18701,"dmgrange":1.00,"dura":70,"reqlevel":18,"sellprice":1323,"sheathtype":4,"slotbak":14]]></jsonEquip><link>https://classic.wowhead.com/item=6572</link></item></wowhead>