<?xml version="1.0" encoding="UTF-8"?><wowhead><item id="15227"><name><![CDATA[Diamond-Tip Bludgeon]]></name><level>49</level><quality id="2">Uncommon</quality><class id="2"><![CDATA[Weapons]]></class><subclass id="4"><![CDATA[One-Handed Maces]]></subclass><icon displayId="28508">inv_mace_15</icon><inventorySlot id="13">One-Hand</inventorySlot><htmlTooltip><![CDATA[<table><tr><td><!--nstart--><b class="q2">Diamond-Tip Bludgeon</b><!--nend--><!--ndstart--><!--ndend--><span class="q"><br>Item Level <!--ilvl-->49</span><br /><!--bo-->Binds when equipped<table width="100%"><tr><td>One-Hand</td><th><!--scstart2:4--><span class="q1">Mace</span><!--scend--></th></tr></table><table width="100%"><tr>
    <td><span><!--dmg-->49 - 91 Damage</span></td>
    <th>Speed <!--spd-->2.40</th>
</tr></table><!--dps-->(29.17 damage per second)<br><!--re--><span class="q2">&lt;Random enchantment&gt;</span><!--ebstats--><!--egstats--><!--eistats--><!--e--><!--ps--><br>Durability 75 / 75</td></tr></table><table><tr><td>Requires Level <!--rlvl-->44<!--itemEffects:1--><div class="whtt-sellprice">Sell Price: <span class="moneygold">2</span> <span class="moneysilver">19</span> <span class="moneycopper">25</span></div></td></tr></table>]]></htmlTooltip><json><![CDATA["classs":2,"commondrop":true,"displayid":28508,"dps":29.17,"flags2":8192,"id":15227,"level":49,"name":"Diamond-Tip Bludgeon","quality":2,"reqlevel":44,"slot":13,"slotbak":13,"source":[2],"speed":2.40,"subclass":4]]></json><jsonEquip><![CDATA["avgbuyout":33000,"displayid":28508,"dmgmax1":91,"dmgmin1":49,"dmgrange":1.00,"dmgtype1":0,"dps":29.17,"dura":75,"mledmgmax":91,"mledmgmin":49,"mledps":29.17,"mlespeed":2.40,"reqlevel":44,"sellprice":21925,"sheathtype":3,"slotbak":13,"speed":2.40]]></jsonEquip><link>https://classic.wowhead.com/item=15227</link></item></wowhead>