<?xml version="1.0" encoding="UTF-8"?><wowhead><item id="22348"><name><![CDATA[Doomulus Prime]]></name><level>65</level><quality id="3">Rare</quality><class id="2"><![CDATA[Weapons]]></class><subclass id="5"><![CDATA[Two-Handed Maces]]></subclass><icon displayId="35010">inv_hammer_10</icon><inventorySlot id="17">Two-Hand</inventorySlot><htmlTooltip><![CDATA[<table><tr><td><!--nstart--><b class="q3">Doomulus Prime</b><!--nend--><!--ndstart--><!--ndend--><span class="q"><br>Item Level <!--ilvl-->65</span><br /><!--bo-->Binds when picked up<table width="100%"><tr><td>Two-Hand</td><th><!--scstart2:5--><span class="q1">Mace</span><!--scend--></th></tr></table><table width="100%"><tr>
    <td><span><!--dmg-->158 - 265 Damage</span></td>
    <th>Speed <!--spd-->3.80</th>
</tr></table><!--dps-->(55.66 damage per second)<br><span><!--stat4-->+22 Strength</span><br><span><!--stat7-->+22 Stamina</span><!--ebstats--><!--egstats--><!--eistats--><!--e--><!--ps--><br>Durability 100 / 100</td></tr></table><table><tr><td><span class="q2">Equip: <a href="https://classic.wowhead.com/spell=15464" class="q2">Improves your chance to hit by 1%.</a></span><!--itemEffects:1--><div class="whtt-sellprice">Sell Price: <span class="moneygold">7</span> <span class="moneysilver">65</span> <span class="moneycopper">7</span></div></td></tr></table>]]></htmlTooltip><json><![CDATA["classs":2,"displayid":35010,"dps":55.66,"flags2":8192,"id":22348,"level":65,"name":"Doomulus Prime","quality":3,"reqlevel":60,"slot":17,"slotbak":17,"source":[4],"sourcemore":[{"c":1377,"c2":1,"n":"The Perfect Poison","t":5,"ti":9023}],"speed":3.80,"subclass":5]]></json><jsonEquip><![CDATA["displayid":35010,"dmgmax1":265,"dmgmin1":158,"dmgrange":1.00,"dmgtype1":0,"dps":55.66,"dura":100,"mledmgmax":265,"mledmgmin":158,"mledps":55.66,"mlehitpct":1,"mlespeed":3.80,"rgdhitpct":1,"sellprice":76507,"sheathtype":1,"slotbak":17,"speed":3.80,"sta":22,"str":22]]></jsonEquip><link>https://classic.wowhead.com/item=22348</link></item></wowhead>