<?xml version="1.0" encoding="UTF-8"?><wowhead><item id="1405"><name><![CDATA[Foamspittle Staff]]></name><level>17</level><quality id="2">Uncommon</quality><class id="2"><![CDATA[Weapons]]></class><subclass id="10"><![CDATA[Staves]]></subclass><icon displayId="5540">inv_staff_06</icon><inventorySlot id="17">Two-Hand</inventorySlot><htmlTooltip><![CDATA[<table><tr><td><!--nstart--><b class="q2">Foamspittle Staff</b><!--nend--><!--ndstart--><!--ndend--><span class="q"><br>Item Level <!--ilvl-->17</span><br /><!--bo-->Binds when equipped<table width="100%"><tr><td>Two-Hand</td><th><!--scstart2:10--><span class="q1">Staff</span><!--scend--></th></tr></table><table width="100%"><tr>
    <td><span><!--dmg-->29 - 44 Damage</span></td>
    <th>Speed <!--spd-->3.20</th>
</tr></table><!--dps-->(11.41 damage per second)<br><span><!--stat6-->+5 Spirit</span><!--ebstats--><!--egstats--><!--eistats--><!--e--><!--ps--><br>Durability 60 / 60</td></tr></table><table><tr><td>Requires Level <!--rlvl-->12<!--itemEffects:1--><div class="whtt-sellprice">Sell Price: <span class="moneysilver">11</span> <span class="moneycopper">84</span></div><div class="whtt-extra whtt-droppedby">Dropped by: Murloc Oracle</div><div class="whtt-extra whtt-dropchance">Drop Chance: 1.44%</div></td></tr></table>]]></htmlTooltip><json><![CDATA["classs":2,"displayid":5540,"dps":11.41,"flags2":8192,"id":1405,"level":17,"name":"Foamspittle Staff","quality":2,"reqlevel":12,"slot":17,"slotbak":17,"source":[2],"sourcemore":[{"n":"Murloc Oracle","t":1,"ti":517,"z":40}],"speed":3.20,"subclass":10]]></json><jsonEquip><![CDATA["avgbuyout":2617,"displayid":5540,"dmgmax1":44,"dmgmin1":29,"dmgrange":1.00,"dmgtype1":0,"dps":11.41,"dura":60,"mledmgmax":44,"mledmgmin":29,"mledps":11.41,"mlespeed":3.20,"reqlevel":12,"sellprice":1184,"sheathtype":2,"slotbak":17,"speed":3.20,"spi":5]]></jsonEquip><link>https://classic.wowhead.com/item=1405</link></item></wowhead>