<?xml version="1.0" encoding="UTF-8"?><wowhead><item id="15633"><name><![CDATA[Formidable Crest]]></name><level>52</level><quality id="2">Uncommon</quality><class id="4"><![CDATA[Armor]]></class><subclass id="6"><![CDATA[Shields]]></subclass><icon displayId="27222">inv_shield_04</icon><inventorySlot id="14">Shield</inventorySlot><htmlTooltip><![CDATA[<table><tr><td><!--nstart--><b class="q2">Formidable Crest</b><!--nend--><!--ndstart--><!--ndend--><span class="q"><br>Item Level <!--ilvl-->52</span><br /><!--bo-->Binds when equipped<table width="100%"><tr><td>Off Hand</td><th><!--scstart4:6--><span class="q1">Shield</span><!--scend--></th></tr></table><span><!--amr-->1606 Armor</span><br>26 Block<br><!--re--><span class="q2">&lt;Random enchantment&gt;</span><!--ebstats--><!--egstats--><!--eistats--><!--e--><!--ps--><br>Durability 85 / 85</td></tr></table><table><tr><td>Requires Level <!--rlvl-->47<!--itemEffects:1--><div class="whtt-sellprice">Sell Price: <span class="moneygold">1</span> <span class="moneysilver">62</span> <span class="moneycopper">10</span></div></td></tr></table>]]></htmlTooltip><json><![CDATA["armor":1606,"classs":4,"displayid":27222,"flags2":8192,"id":15633,"level":52,"name":"Formidable Crest","quality":2,"reqlevel":47,"slot":14,"slotbak":14,"source":[2],"subclass":6]]></json><jsonEquip><![CDATA["armor":1606,"avgbuyout":45000,"blockamount":26,"displayid":27222,"dmgrange":1.00,"dura":85,"reqlevel":47,"sellprice":16210,"sheathtype":4,"slotbak":14]]></jsonEquip><link>https://classic.wowhead.com/item=15633</link></item></wowhead>