<?xml version="1.0" encoding="UTF-8"?><wowhead><item id="12542"><name><![CDATA[Funeral Pyre Vestment]]></name><level>51</level><quality id="3">Rare</quality><class id="4"><![CDATA[Armor]]></class><subclass id="1"><![CDATA[Cloth Armor]]></subclass><icon displayId="26053">inv_chest_cloth_40</icon><inventorySlot id="5">Chest</inventorySlot><htmlTooltip><![CDATA[<table><tr><td><!--nstart--><b class="q3">Funeral Pyre Vestment</b><!--nend--><!--ndstart--><!--ndend--><span class="q"><br>Item Level <!--ilvl-->51</span><br /><!--bo-->Binds when equipped<table width="100%"><tr><td>Chest</td><th><!--scstart4:1--><span class="q1">Cloth</span><!--scend--></th></tr></table><span><!--amr-->73 Armor</span><br><span><!--stat5-->+13 Intellect</span><br><span><!--stat7-->+13 Stamina</span><br><span><!--stat6-->+13 Spirit</span><!--ebstats--><!--egstats--><!--eistats--><br>+10 Fire Resistance<!--e--><!--ps--><br>Durability 80 / 80</td></tr></table><table><tr><td>Requires Level <!--rlvl-->46<!--itemEffects:1--><div class="whtt-sellprice">Sell Price: <span class="moneygold">1</span> <span class="moneysilver">23</span> <span class="moneycopper">56</span></div></td></tr></table>]]></htmlTooltip><json><![CDATA["armor":73,"classs":4,"displayid":26053,"flags2":8192,"id":12542,"level":51,"name":"Funeral Pyre Vestment","quality":3,"reqlevel":46,"slot":5,"slotbak":20,"source":[2],"sourcemore":[{"dd":-1,"z":1584}],"subclass":1]]></json><jsonEquip><![CDATA["armor":73,"avgbuyout":92625,"displayid":26053,"dmgrange":1.00,"dura":80,"firres":10,"int":13,"reqlevel":46,"sellprice":12356,"slotbak":20,"spi":13,"sta":13]]></jsonEquip><link>https://classic.wowhead.com/item=12542</link></item></wowhead>