<?xml version="1.0" encoding="UTF-8"?><wowhead><item id="15262"><name><![CDATA[Greater Maul]]></name><level>46</level><quality id="2">Uncommon</quality><class id="2"><![CDATA[Weapons]]></class><subclass id="5"><![CDATA[Two-Handed Maces]]></subclass><icon displayId="28540">inv_hammer_19</icon><inventorySlot id="17">Two-Hand</inventorySlot><htmlTooltip><![CDATA[<table><tr><td><!--nstart--><b class="q2">Greater Maul</b><!--nend--><!--ndstart--><!--ndend--><span class="q"><br>Item Level <!--ilvl-->46</span><br /><!--bo-->Binds when equipped<table width="100%"><tr><td>Two-Hand</td><th><!--scstart2:5--><span class="q1">Mace</span><!--scend--></th></tr></table><table width="100%"><tr>
    <td><span><!--dmg-->97 - 146 Damage</span></td>
    <th>Speed <!--spd-->3.40</th>
</tr></table><!--dps-->(35.74 damage per second)<br><!--re--><span class="q2">&lt;Random enchantment&gt;</span><!--ebstats--><!--egstats--><!--eistats--><!--e--><!--ps--><br>Durability 85 / 85</td></tr></table><table><tr><td>Requires Level <!--rlvl-->41<!--itemEffects:1--><div class="whtt-sellprice">Sell Price: <span class="moneygold">2</span> <span class="moneysilver">15</span> <span class="moneycopper">52</span></div></td></tr></table>]]></htmlTooltip><json><![CDATA["classs":2,"commondrop":true,"displayid":28540,"dps":35.74,"flags2":8192,"id":15262,"level":46,"name":"Greater Maul","quality":2,"reqlevel":41,"slot":17,"slotbak":17,"source":[2],"speed":3.40,"subclass":5]]></json><jsonEquip><![CDATA["avgbuyout":31500,"displayid":28540,"dmgmax1":146,"dmgmin1":97,"dmgrange":1.00,"dmgtype1":0,"dps":35.74,"dura":85,"mledmgmax":146,"mledmgmin":97,"mledps":35.74,"mlespeed":3.40,"reqlevel":41,"sellprice":21552,"sheathtype":1,"slotbak":17,"speed":3.40]]></jsonEquip><link>https://classic.wowhead.com/item=15262</link></item></wowhead>