<?xml version="1.0" encoding="UTF-8"?><wowhead><item id="18717"><name><![CDATA[Hammer of the Grand Crusader]]></name><level>63</level><quality id="3">Rare</quality><class id="2"><![CDATA[Weapons]]></class><subclass id="5"><![CDATA[Two-Handed Maces]]></subclass><icon displayId="23239">inv_hammer_06</icon><inventorySlot id="17">Two-Hand</inventorySlot><htmlTooltip><![CDATA[<table><tr><td><!--nstart--><b class="q3">Hammer of the Grand Crusader</b><!--nend--><!--ndstart--><!--ndend--><span class="q"><br>Item Level <!--ilvl-->63</span><br /><!--bo-->Binds when picked up<table width="100%"><tr><td>Two-Hand</td><th><!--scstart2:5--><span class="q1">Mace</span><!--scend--></th></tr></table><table width="100%"><tr>
    <td><span><!--dmg-->116 - 175 Damage</span></td>
    <th>Speed <!--spd-->2.70</th>
</tr></table><!--dps-->(53.89 damage per second)<br><span><!--stat5-->+26 Intellect</span><br><span><!--stat7-->+10 Stamina</span><br><span><!--stat6-->+9 Spirit</span><!--ebstats--><!--egstats--><!--eistats--><!--e--><!--ps--><br>Durability 100 / 100</td></tr></table><table><tr><td>Requires Level <!--rlvl-->58<br><span class="q2">Equip: <a href="https://classic.wowhead.com/spell=9408" class="q2">Increases healing done by spells and effects by up to 22.</a></span><!--itemEffects:1--><div class="whtt-sellprice">Sell Price: <span class="moneygold">6</span> <span class="moneysilver">88</span> <span class="moneycopper">18</span></div></td></tr></table>]]></htmlTooltip><json><![CDATA["classs":2,"displayid":23239,"dps":53.89,"flags2":8192,"id":18717,"level":63,"name":"Hammer of the Grand Crusader","quality":3,"reqlevel":58,"slot":17,"slotbak":17,"source":[2],"sourcemore":[{"dd":-1,"z":2017}],"speed":2.70,"subclass":5]]></json><jsonEquip><![CDATA["displayid":23239,"dmgmax1":175,"dmgmin1":116,"dmgrange":1.00,"dmgtype1":0,"dps":53.89,"dura":100,"int":26,"mledmgmax":175,"mledmgmin":116,"mledps":53.89,"mlespeed":2.70,"reqlevel":58,"sellprice":68818,"sheathtype":1,"slotbak":17,"speed":2.70,"spi":9,"splheal":22,"sta":10]]></jsonEquip><link>https://classic.wowhead.com/item=18717</link></item></wowhead>