<?xml version="1.0" encoding="UTF-8"?><wowhead><item id="7786"><name><![CDATA[Headsplitter]]></name><level>30</level><quality id="3">Rare</quality><class id="2"><![CDATA[Weapons]]></class><subclass id="0"><![CDATA[One-Handed Axes]]></subclass><icon displayId="15938">inv_axe_14</icon><inventorySlot id="13">One-Hand</inventorySlot><htmlTooltip><![CDATA[<table><tr><td><!--nstart--><b class="q3">Headsplitter</b><!--nend--><!--ndstart--><!--ndend--><span class="q"><br>Item Level <!--ilvl-->30</span><br /><!--bo-->Binds when equipped<table width="100%"><tr><td>One-Hand</td><th><!--scstart2:0--><span class="q1">Axe</span><!--scend--></th></tr></table><table width="100%"><tr>
    <td><span><!--dmg-->30 - 57 Damage</span></td>
    <th>Speed <!--spd-->2.30</th>
</tr></table><!--dps-->(18.91 damage per second)<br><span><!--stat4-->+3 Strength</span><br><span><!--stat7-->+5 Stamina</span><!--ebstats--><!--egstats--><!--eistats--><!--e--><!--ps--><br>Durability 90 / 90</td></tr></table><table><tr><td>Requires Level <!--rlvl-->25<!--itemEffects:1--><div class="whtt-sellprice">Sell Price: <span class="moneysilver">56</span> <span class="moneycopper">5</span></div></td></tr></table>]]></htmlTooltip><json><![CDATA["classs":2,"displayid":15938,"dps":18.91,"flags2":8192,"id":7786,"level":30,"name":"Headsplitter","quality":3,"reqlevel":25,"slot":13,"slotbak":13,"source":[2],"speed":2.30,"subclass":0]]></json><jsonEquip><![CDATA["avgbuyout":28800,"displayid":15938,"dmgmax1":57,"dmgmin1":30,"dmgrange":1.00,"dmgtype1":0,"dps":18.91,"dura":90,"mledmgmax":57,"mledmgmin":30,"mledps":18.91,"mlespeed":2.30,"reqlevel":25,"sellprice":5605,"sheathtype":3,"slotbak":13,"speed":2.30,"sta":5,"str":3]]></jsonEquip><link>https://classic.wowhead.com/item=7786</link></item></wowhead>