<?xml version="1.0" encoding="UTF-8"?><wowhead><item id="20059"><name><![CDATA[Highlander's Leather Shoulders]]></name><level>65</level><quality id="4">Epic</quality><class id="4"><![CDATA[Armor]]></class><subclass id="2"><![CDATA[Leather Armor]]></subclass><icon displayId="18971">inv_shoulder_24</icon><inventorySlot id="3">Shoulder</inventorySlot><htmlTooltip><![CDATA[<table><tr><td><!--nstart--><b class="q4">Highlander's Leather Shoulders</b><!--nend--><!--ndstart--><!--ndend--><span class="q"><br>Item Level <!--ilvl-->65</span><br /><!--bo-->Binds when picked up<br />Unique<table width="100%"><tr><td>Shoulder</td><th><!--scstart4:2--><span class="q1">Leather</span><!--scend--></th></tr></table><span><!--amr-->258 Armor</span><br><span><!--stat3-->+18 Agility</span><br><span><!--stat7-->+17 Stamina</span><!--ebstats--><!--egstats--><!--eistats--><!--e--><!--ps--><br>Durability 70 / 70<div class="wowhead-tooltip-item-classes">Classes: <a href="https://classic.wowhead.com/class=4" class="c4">Rogue</a>, <a href="https://classic.wowhead.com/class=11" class="c11">Druid</a></div></td></tr></table><table><tr><td>Requires Level <!--rlvl-->60<br>Requires <a href="https://classic.wowhead.com/faction=509" class="q1">The League of Arathor</a> - Exalted<br><span class="q2">Equip: <a href="https://classic.wowhead.com/spell=9336" class="q2">+30 Attack Power.</a></span><!--itemEffects:1--><br /><br /><span class="q"><a href="https://classic.wowhead.com/item-set=471" class="q">The Highlander's Purpose</a> (0/3)</span><div class="q0 indent"><span><!--si20052--><a href="https://classic.wowhead.com/item=20052">Highlander's Leather Boots</a></span><br /><span><!--si20045--><a href="https://classic.wowhead.com/item=20045">Highlander's Leather Girdle</a></span><br /><span><!--si20059--><a href="https://classic.wowhead.com/item=20059">Highlander's Leather Shoulders</a></span></div><br /><span class="q0"><span>(2) Set : <a href="https://classic.wowhead.com/spell=7503">+5 Stamina.</a></span><br /><span>(3) Set : <a href="https://classic.wowhead.com/spell=7597">Improves your chance to get a critical strike by 1%.</a></span></span><div class="whtt-sellprice">Sell Price: <span class="moneygold">3</span> <span class="moneysilver">18</span> <span class="moneycopper">94</span></div></td></tr></table>]]></htmlTooltip><json><![CDATA["armor":258,"classs":4,"displayid":18971,"flags2":8192,"id":20059,"level":65,"name":"Highlander's Leather Shoulders","quality":4,"reqclass":1032,"reqlevel":60,"slot":3,"slotbak":3,"source":[5],"sourcemore":[{"n":"Samuel Hawke","t":1,"ti":15127,"z":45}],"subclass":2]]></json><jsonEquip><![CDATA["agi":18,"armor":258,"atkpwr":30,"buyprice":159473,"classes":1032,"displayid":18971,"dmgrange":1.00,"dura":70,"itemset":471,"maxcount":1,"reqfaction":509,"reqlevel":60,"reqrep":7,"sellprice":31894,"slotbak":3,"sta":17]]></jsonEquip><link>https://classic.wowhead.com/item=20059</link></item></wowhead>