<?xml version="1.0" encoding="UTF-8"?><wowhead><item id="2975"><name><![CDATA[Hunting Boots]]></name><level>14</level><quality id="1">Common</quality><class id="4"><![CDATA[Armor]]></class><subclass id="2"><![CDATA[Leather Armor]]></subclass><icon displayId="14534">inv_boots_wolf</icon><inventorySlot id="8">Feet</inventorySlot><htmlTooltip><![CDATA[<table><tr><td><!--nstart--><b class="q1">Hunting Boots</b><!--nend--><!--ndstart--><!--ndend--><span class="q"><br>Item Level <!--ilvl-->14</span><table width="100%"><tr><td>Feet</td><th><!--scstart4:2--><span class="q1">Leather</span><!--scend--></th></tr></table><span><!--amr-->45 Armor</span><!--ebstats--><!--egstats--><!--eistats--><!--e--><!--ps--><br>Durability 30 / 30</td></tr></table><table><tr><td>Requires Level <!--rlvl-->9<!--itemEffects:1--><div class="whtt-sellprice">Sell Price: <span class="moneysilver">1</span> <span class="moneycopper">28</span></div></td></tr></table>]]></htmlTooltip><json><![CDATA["armor":45,"classs":4,"displayid":14534,"flags2":8192,"id":2975,"level":14,"name":"Hunting Boots","quality":1,"reqlevel":9,"slot":8,"slotbak":8,"source":[2,16],"subclass":2]]></json><jsonEquip><![CDATA["armor":45,"avgbuyout":495,"displayid":14534,"dmgrange":1.00,"dura":30,"reqlevel":9,"sellprice":128,"slotbak":8]]></jsonEquip><link>https://classic.wowhead.com/item=2975</link></item></wowhead>