<?xml version="1.0" encoding="UTF-8"?><wowhead><item id="1744"><name><![CDATA[Laced Mail Shoulderpads]]></name><level>20</level><quality id="0">Poor</quality><class id="4"><![CDATA[Armor]]></class><subclass id="3"><![CDATA[Mail Armor]]></subclass><icon displayId="6914">inv_shoulder_07</icon><inventorySlot id="3">Shoulder</inventorySlot><htmlTooltip><![CDATA[<table><tr><td><!--nstart--><b class="q0">Laced Mail Shoulderpads</b><!--nend--><!--ndstart--><!--ndend--><span class="q"><br>Item Level <!--ilvl-->20</span><table width="100%"><tr><td>Shoulder</td><th><!--scstart4:3--><span class="q1">Mail</span><!--scend--></th></tr></table><span><!--amr-->113 Armor</span><!--ebstats--><!--egstats--><!--eistats--><!--e--><!--ps--><br>Durability 50 / 50</td></tr></table><table><tr><td>Requires Level <!--rlvl-->15<!--itemEffects:1--><div class="whtt-sellprice">Sell Price: <span class="moneysilver">2</span> <span class="moneycopper">60</span></div></td></tr></table>]]></htmlTooltip><json><![CDATA["armor":113,"classs":4,"commondrop":true,"displayid":6914,"flags2":8192,"id":1744,"level":20,"name":"Laced Mail Shoulderpads","quality":0,"reqlevel":15,"slot":3,"slotbak":3,"source":[2],"subclass":3]]></json><jsonEquip><![CDATA["armor":113,"avgbuyout":1500,"displayid":6914,"dmgrange":1.00,"dura":50,"reqlevel":15,"sellprice":260,"slotbak":3]]></jsonEquip><link>https://classic.wowhead.com/item=1744</link></item></wowhead>