<?xml version="1.0" encoding="UTF-8"?><wowhead><item id="15061"><name><![CDATA[Living Shoulders]]></name><level>54</level><quality id="3">Rare</quality><class id="4"><![CDATA[Armor]]></class><subclass id="2"><![CDATA[Leather Armor]]></subclass><icon displayId="25695">inv_shoulder_18</icon><inventorySlot id="3">Shoulder</inventorySlot><htmlTooltip><![CDATA[<table><tr><td><!--nstart--><b class="q3">Living Shoulders</b><!--nend--><!--ndstart--><!--ndend--><span class="q"><br>Item Level <!--ilvl-->54</span><br /><!--bo-->Binds when equipped<table width="100%"><tr><td>Shoulder</td><th><!--scstart4:2--><span class="q1">Leather</span><!--scend--></th></tr></table><span><!--amr-->117 Armor</span><br><span><!--stat7-->+8 Stamina</span><br><span><!--stat6-->+13 Spirit</span><!--ebstats--><!--egstats--><!--eistats--><br>+3 Nature Resistance<!--e--><!--ps--><br>Durability 60 / 60</td></tr></table><table><tr><td>Requires Level <!--rlvl-->49<br><span class="q2">Equip: <a href="https://classic.wowhead.com/spell=9317" class="q2">Increases healing done by spells and effects by up to 31.</a></span><!--itemEffects:1--><div class="whtt-sellprice">Sell Price: <span class="moneygold">1</span> <span class="moneysilver">38</span> <span class="moneycopper">3</span></div></td></tr></table>]]></htmlTooltip><json><![CDATA["armor":117,"classs":4,"displayid":25695,"flags2":8192,"id":15061,"level":54,"name":"Living Shoulders","quality":3,"reqlevel":49,"slot":3,"slotbak":3,"source":[1],"sourcemore":[{"c":11,"icon":"inv_shoulder_18","n":"Living Shoulders","s":165,"t":6,"ti":19061}],"subclass":2]]></json><jsonEquip><![CDATA["armor":117,"avgbuyout":220000,"displayid":25695,"dmgrange":1.00,"dura":60,"natres":3,"reqlevel":49,"sellprice":13803,"slotbak":3,"spi":13,"splheal":31,"sta":8]]></jsonEquip><createdBy><spell id="19061" name="Living Shoulders" icon="inv_shoulder_18" minCount="0" maxCount="0"><reagent id="8170" name="Rugged Leather" quality="1" icon="inv_misc_leatherscrap_02" count="12" /><reagent id="12803" name="Living Essence" quality="2" icon="spell_nature_abolishmagic" count="4" /><reagent id="14341" name="Rune Thread" quality="1" icon="spell_shadow_antimagicshell" count="1" /></spell></createdBy><link>https://classic.wowhead.com/item=15061</link></item></wowhead>