<?xml version="1.0" encoding="UTF-8"?><wowhead><item id="10155"><name><![CDATA[Mercurial Greaves]]></name><level>61</level><quality id="2">Uncommon</quality><class id="4"><![CDATA[Armor]]></class><subclass id="3"><![CDATA[Mail Armor]]></subclass><icon displayId="26129">inv_boots_02</icon><inventorySlot id="8">Feet</inventorySlot><htmlTooltip><![CDATA[<table><tr><td><!--nstart--><b class="q2">Mercurial Greaves</b><!--nend--><!--ndstart--><!--ndend--><span class="q"><br>Item Level <!--ilvl-->61</span><br /><!--bo-->Binds when equipped<table width="100%"><tr><td>Feet</td><th><!--scstart4:3--><span class="q1">Mail</span><!--scend--></th></tr></table><span><!--amr-->225 Armor</span><br><!--re--><span class="q2">&lt;Random enchantment&gt;</span><!--ebstats--><!--egstats--><!--eistats--><!--e--><!--ps--><br>Durability 50 / 50</td></tr></table><table><tr><td>Requires Level <!--rlvl-->56<!--itemEffects:1--><div class="whtt-sellprice">Sell Price: <span class="moneygold">2</span> <span class="moneysilver">1</span> <span class="moneycopper">68</span></div></td></tr></table>]]></htmlTooltip><json><![CDATA["armor":225,"classs":4,"commondrop":true,"displayid":26129,"flags2":8192,"id":10155,"level":61,"name":"Mercurial Greaves","quality":2,"reqlevel":56,"slot":8,"slotbak":8,"source":[2],"subclass":3]]></json><jsonEquip><![CDATA["armor":225,"avgbuyout":43987,"displayid":26129,"dmgrange":1.00,"dura":50,"reqlevel":56,"sellprice":20168,"slotbak":8]]></jsonEquip><link>https://classic.wowhead.com/item=10155</link></item></wowhead>