<?xml version="1.0" encoding="UTF-8"?><wowhead><item id="10154"><name><![CDATA[Mercurial Girdle]]></name><level>61</level><quality id="2">Uncommon</quality><class id="4"><![CDATA[Armor]]></class><subclass id="3"><![CDATA[Mail Armor]]></subclass><icon displayId="26127">inv_belt_11</icon><inventorySlot id="6">Waist</inventorySlot><htmlTooltip><![CDATA[<table><tr><td><!--nstart--><b class="q2">Mercurial Girdle</b><!--nend--><!--ndstart--><!--ndend--><span class="q"><br>Item Level <!--ilvl-->61</span><br /><!--bo-->Binds when equipped<table width="100%"><tr><td>Waist</td><th><!--scstart4:3--><span class="q1">Mail</span><!--scend--></th></tr></table><span><!--amr-->184 Armor</span><br><!--re--><span class="q2">&lt;Random enchantment&gt;</span><!--ebstats--><!--egstats--><!--eistats--><!--e--><!--ps--><br>Durability 35 / 35</td></tr></table><table><tr><td>Requires Level <!--rlvl-->56<!--itemEffects:1--><div class="whtt-sellprice">Sell Price: <span class="moneygold">1</span> <span class="moneysilver">33</span> <span class="moneycopper">37</span></div></td></tr></table>]]></htmlTooltip><json><![CDATA["armor":184,"classs":4,"commondrop":true,"displayid":26127,"flags2":8192,"id":10154,"level":61,"name":"Mercurial Girdle","quality":2,"reqlevel":56,"slot":6,"slotbak":6,"source":[2],"subclass":3]]></json><jsonEquip><![CDATA["armor":184,"avgbuyout":34657,"displayid":26127,"dmgrange":1.00,"dura":35,"reqlevel":56,"sellprice":13337,"slotbak":6]]></jsonEquip><link>https://classic.wowhead.com/item=10154</link></item></wowhead>