<?xml version="1.0" encoding="UTF-8"?><wowhead><item id="4315"><name><![CDATA[Reinforced Woolen Shoulders]]></name><level>24</level><quality id="1">Common</quality><class id="4"><![CDATA[Armor]]></class><subclass id="1"><![CDATA[Cloth Armor]]></subclass><icon displayId="17135">inv_shoulder_09</icon><inventorySlot id="3">Shoulder</inventorySlot><htmlTooltip><![CDATA[<table><tr><td><!--nstart--><b class="q1">Reinforced Woolen Shoulders</b><!--nend--><!--ndstart--><!--ndend--><span class="q"><br>Item Level <!--ilvl-->24</span><table width="100%"><tr><td>Shoulder</td><th><!--scstart4:1--><span class="q1">Cloth</span><!--scend--></th></tr></table><span><!--amr-->27 Armor</span><!--ebstats--><!--egstats--><!--eistats--><!--e--><!--ps--><br>Durability 40 / 40</td></tr></table><table><tr><td>Requires Level <!--rlvl-->19<!--itemEffects:1--><div class="whtt-sellprice">Sell Price: <span class="moneysilver">4</span> <span class="moneycopper">25</span></div></td></tr></table>]]></htmlTooltip><json><![CDATA["armor":27,"classs":4,"displayid":17135,"flags2":8192,"id":4315,"level":24,"name":"Reinforced Woolen Shoulders","quality":1,"reqlevel":19,"slot":3,"slotbak":3,"source":[1],"sourcemore":[{"c":11,"icon":"inv_shoulder_09","n":"Reinforced Woolen Shoulders","s":197,"t":6,"ti":3849}],"subclass":1]]></json><jsonEquip><![CDATA["armor":27,"avgbuyout":500,"displayid":17135,"dmgrange":1.00,"dura":40,"reqlevel":19,"sellprice":425,"slotbak":3]]></jsonEquip><createdBy><spell id="3849" name="Reinforced Woolen Shoulders" icon="inv_shoulder_09" minCount="0" maxCount="0"><reagent id="2997" name="Bolt of Woolen Cloth" quality="1" icon="inv_fabric_wool_03" count="6" /><reagent id="2319" name="Medium Leather" quality="1" icon="inv_misc_leatherscrap_05" count="2" /><reagent id="2321" name="Fine Thread" quality="1" icon="inv_fabric_wool_02" count="2" /></spell></createdBy><link>https://classic.wowhead.com/item=4315</link></item></wowhead>