<?xml version="1.0" encoding="UTF-8"?><wowhead><item id="9704"><name><![CDATA[Rustler Gloves]]></name><level>43</level><quality id="2">Uncommon</quality><class id="4"><![CDATA[Armor]]></class><subclass id="2"><![CDATA[Leather Armor]]></subclass><icon displayId="28296">inv_gauntlets_23</icon><inventorySlot id="10">Hands</inventorySlot><htmlTooltip><![CDATA[<table><tr><td><!--nstart--><b class="q2">Rustler Gloves</b><!--nend--><!--ndstart--><!--ndend--><span class="q"><br>Item Level <!--ilvl-->43</span><br /><!--bo-->Binds when picked up<table width="100%"><tr><td>Hands</td><th><!--scstart4:2--><span class="q1">Leather</span><!--scend--></th></tr></table><span><!--amr-->73 Armor</span><br><span><!--stat4-->+9 Strength</span><br><span><!--stat5-->+9 Intellect</span><!--ebstats--><!--egstats--><!--eistats--><!--e--><!--ps--><br>Durability 30 / 30</td></tr></table><table><tr><td><!--itemEffects:0--><div class="whtt-sellprice">Sell Price: <span class="moneysilver">35</span> <span class="moneycopper">73</span></div></td></tr></table>]]></htmlTooltip><json><![CDATA["armor":73,"classs":4,"displayid":28296,"flags2":8192,"id":9704,"level":43,"name":"Rustler Gloves","quality":2,"reqlevel":38,"side":2,"slot":10,"slotbak":10,"source":[4],"sourcemore":[{"c":15,"c2":1,"n":"Identifying the Brood","t":5,"ti":1169}],"subclass":2]]></json><jsonEquip><![CDATA["armor":73,"displayid":28296,"dmgrange":1.00,"dura":30,"int":9,"sellprice":3573,"slotbak":10,"str":9]]></jsonEquip><link>https://classic.wowhead.com/item=9704</link></item></wowhead>