<?xml version="1.0" encoding="UTF-8"?><wowhead><item id="4616"><name><![CDATA[Ryedol's Lucky Pick]]></name><level>1</level><quality id="1">Common</quality><class id="2"><![CDATA[Weapons]]></class><subclass id="14"><![CDATA[Miscellaneous (Weapons)]]></subclass><icon displayId="6589">inv_pick_03</icon><inventorySlot id="13">One-Hand</inventorySlot><htmlTooltip><![CDATA[<table><tr><td><!--nstart--><b class="q1">Ryedol's Lucky Pick</b><!--nend--><!--ndstart--><!--ndend--><span class="q"><br>Item Level <!--ilvl-->1</span><br /><!--bo-->Quest Item<br />Unique<table width="100%"><tr><td>One-Hand</td></table><table width="100%"><tr>
    <td><span><!--dmg-->1 - 2 Damage</span></td>
    <th>Speed <!--spd-->1.50</th>
</tr></table><!--dps-->(1.00 damage per second)<!--ebstats--><!--egstats--><!--eistats--><!--e--><!--ps--></td></tr></table><table><tr><td><!--itemEffects:0--><div class="whtt-sellprice">Sell Price: <span class="moneycopper">3</span></div></td></tr></table>]]></htmlTooltip><json><![CDATA["classs":2,"displayid":6589,"dps":1.00,"flags2":8192,"id":4616,"level":1,"name":"Ryedol's Lucky Pick","quality":1,"slot":13,"slotbak":13,"source":[2],"sourcemore":[{"dd":-1,"z":3}],"speed":1.50,"subclass":14]]></json><jsonEquip><![CDATA["displayid":6589,"dmgmax1":2,"dmgmin1":1,"dmgrange":1.00,"dmgtype1":0,"dps":1.00,"maxcount":1,"mledmgmax":2,"mledmgmin":1,"mledps":1.00,"mlespeed":1.50,"sellprice":3,"sheathtype":3,"slotbak":13,"speed":1.50]]></jsonEquip><link>https://classic.wowhead.com/item=4616</link></item></wowhead>