<?xml version="1.0" encoding="UTF-8"?><wowhead><item id="10331"><name><![CDATA[Scarlet Gauntlets]]></name><level>38</level><quality id="2">Uncommon</quality><class id="4"><![CDATA[Armor]]></class><subclass id="3"><![CDATA[Mail Armor]]></subclass><icon displayId="15816">inv_gauntlets_19</icon><inventorySlot id="10">Hands</inventorySlot><htmlTooltip><![CDATA[<table><tr><td><!--nstart--><b class="q2">Scarlet Gauntlets</b><!--nend--><!--ndstart--><!--ndend--><span class="q"><br>Item Level <!--ilvl-->38</span><br /><!--bo-->Binds when equipped<table width="100%"><tr><td>Hands</td><th><!--scstart4:3--><span class="q1">Mail</span><!--scend--></th></tr></table><span><!--amr-->139 Armor</span><br><span><!--stat4-->+8 Strength</span><br><span><!--stat3-->+7 Agility</span><!--ebstats--><!--egstats--><!--eistats--><!--e--><!--ps--><br>Durability 35 / 35</td></tr></table><table><tr><td>Requires Level <!--rlvl-->33<!--itemEffects:1--><br /><br /><span class="q"><a href="https://classic.wowhead.com/item-set=163" class="q">Chain of the Scarlet Crusade</a> (0/6)</span><div class="q0 indent"><span><!--si10329--><a href="https://classic.wowhead.com/item=10329">Scarlet Belt</a></span><br /><span><!--si10332--><a href="https://classic.wowhead.com/item=10332">Scarlet Boots</a></span><br /><span><!--si10328--><a href="https://classic.wowhead.com/item=10328">Scarlet Chestpiece</a></span><br /><span><!--si10331--><a href="https://classic.wowhead.com/item=10331">Scarlet Gauntlets</a></span><br /><span><!--si10330--><a href="https://classic.wowhead.com/item=10330">Scarlet Leggings</a></span><br /><span><!--si10333--><a href="https://classic.wowhead.com/item=10333">Scarlet Wristguards</a></span></div><br /><span class="q0"><span>(2) Set : <a href="https://classic.wowhead.com/spell=9760">+10 Armor.</a></span><br /><span>(3) Set : <a href="https://classic.wowhead.com/spell=7513">Increased Defense +1.</a></span><br /><span>(4) Set : <a href="https://classic.wowhead.com/spell=14668">+5 Shadow Resistance.</a></span><br /><span>(5) Set : <a href="https://classic.wowhead.com/spell=20606">+15 Attack Power when fighting Undead.</a></span><br /><span>(6) Set : <a href="https://classic.wowhead.com/spell=15464">Improves your chance to hit by 1%.</a></span></span><div class="whtt-sellprice">Sell Price: <span class="moneysilver">27</span> <span class="moneycopper">28</span></div><div class="whtt-extra whtt-droppedby">Dropped by: Scarlet Centurion</div><div class="whtt-extra whtt-dropchance">Drop Chance: 2.65%</div></td></tr></table>]]></htmlTooltip><json><![CDATA["armor":139,"classs":4,"displayid":15816,"flags2":8192,"id":10331,"level":38,"name":"Scarlet Gauntlets","quality":2,"reqlevel":33,"slot":10,"slotbak":10,"source":[2],"sourcemore":[{"dd":-1,"n":"Scarlet Centurion","t":1,"ti":4301,"z":796}],"subclass":3]]></json><jsonEquip><![CDATA["agi":7,"armor":139,"avgbuyout":7900,"displayid":15816,"dmgrange":1.00,"dura":35,"itemset":163,"reqlevel":33,"sellprice":2728,"slotbak":10,"str":8]]></jsonEquip><link>https://classic.wowhead.com/item=10331</link></item></wowhead>