<?xml version="1.0" encoding="UTF-8"?><wowhead><item id="12531"><name><![CDATA[Searing Needle]]></name><level>51</level><quality id="3">Rare</quality><class id="2"><![CDATA[Weapons]]></class><subclass id="15"><![CDATA[Daggers]]></subclass><icon displayId="22721">inv_weapon_shortblade_03</icon><inventorySlot id="13">One-Hand</inventorySlot><htmlTooltip><![CDATA[<table><tr><td><!--nstart--><b class="q3">Searing Needle</b><!--nend--><!--ndstart--><!--ndend--><span class="q"><br>Item Level <!--ilvl-->51</span><br /><!--bo-->Binds when equipped<br />Unique<table width="100%"><tr><td>One-Hand</td><th><!--scstart2:15--><span class="q1">Dagger</span><!--scend--></th></tr></table><table width="100%"><tr>
    <td><span><!--dmg-->42 - 80 Damage</span></td>
    <th>Speed <!--spd-->1.80</th>
</tr></table><!--dps-->(33.89 damage per second)<!--ebstats--><!--egstats--><!--eistats--><!--e--><!--ps--><br>Durability 65 / 65</td></tr></table><table><tr><td>Requires Level <!--rlvl-->46<br><span class="q2">Chance on hit: <a href="https://classic.wowhead.com/spell=16454" class="q2">Blasts a target for 60 Fire damage and increases damage done to target by Fire damage by 10 for 30 sec.</a></span><!--itemEffects:1--><div class="whtt-sellprice">Sell Price: <span class="moneygold">2</span> <span class="moneysilver">88</span> <span class="moneycopper">83</span></div></td></tr></table>]]></htmlTooltip><json><![CDATA["classs":2,"displayid":22721,"dps":33.89,"flags2":8192,"id":12531,"level":51,"name":"Searing Needle","quality":3,"reqlevel":46,"slot":13,"slotbak":13,"source":[2],"sourcemore":[{"dd":-1,"z":1584}],"speed":1.80,"subclass":15]]></json><jsonEquip><![CDATA["avgbuyout":77903,"displayid":22721,"dmgmax1":80,"dmgmin1":42,"dmgrange":1.00,"dmgtype1":0,"dps":33.89,"dura":65,"maxcount":1,"mledmgmax":80,"mledmgmin":42,"mledps":33.89,"mlespeed":1.80,"reqlevel":46,"sellprice":28883,"sheathtype":3,"slotbak":13,"speed":1.80]]></jsonEquip><jsonUse><![CDATA["firsplpwr":10]]></jsonUse><link>https://classic.wowhead.com/item=12531</link></item></wowhead>