<?xml version="1.0" encoding="UTF-8"?><wowhead><item id="2175"><name><![CDATA[Shadowhide Battle Axe]]></name><level>23</level><quality id="2">Uncommon</quality><class id="2"><![CDATA[Weapons]]></class><subclass id="1"><![CDATA[Two-Handed Axes]]></subclass><icon displayId="8534">inv_throwingaxe_06</icon><inventorySlot id="17">Two-Hand</inventorySlot><htmlTooltip><![CDATA[<table><tr><td><!--nstart--><b class="q2">Shadowhide Battle Axe</b><!--nend--><!--ndstart--><!--ndend--><span class="q"><br>Item Level <!--ilvl-->23</span><br /><!--bo-->Binds when equipped<table width="100%"><tr><td>Two-Hand</td><th><!--scstart2:1--><span class="q1">Axe</span><!--scend--></th></tr></table><table width="100%"><tr>
    <td><span><!--dmg-->39 - 59 Damage</span></td>
    <th>Speed <!--spd-->3.20</th>
</tr></table><!--dps-->(15.31 damage per second)<br><span><!--stat4-->+6 Strength</span><br><span><!--stat7-->+3 Stamina</span><!--ebstats--><!--egstats--><!--eistats--><!--e--><!--ps--><br>Durability 70 / 70</td></tr></table><table><tr><td>Requires Level <!--rlvl-->18<!--itemEffects:1--><div class="whtt-sellprice">Sell Price: <span class="moneysilver">26</span> <span class="moneycopper">83</span></div><div class="whtt-extra whtt-droppedby">Dropped by: Shadowhide Warrior</div><div class="whtt-extra whtt-dropchance">Drop Chance: 2.08%</div></td></tr></table>]]></htmlTooltip><json><![CDATA["classs":2,"displayid":8534,"dps":15.31,"flags2":8192,"id":2175,"level":23,"name":"Shadowhide Battle Axe","quality":2,"reqlevel":18,"slot":17,"slotbak":17,"source":[2],"sourcemore":[{"n":"Shadowhide Warrior","t":1,"ti":568,"z":44}],"speed":3.20,"subclass":1]]></json><jsonEquip><![CDATA["avgbuyout":3700,"displayid":8534,"dmgmax1":59,"dmgmin1":39,"dmgrange":1.00,"dmgtype1":0,"dps":15.31,"dura":70,"mledmgmax":59,"mledmgmin":39,"mledps":15.31,"mlespeed":3.20,"reqlevel":18,"sellprice":2683,"sheathtype":1,"slotbak":17,"speed":3.20,"sta":3,"str":6]]></jsonEquip><link>https://classic.wowhead.com/item=2175</link></item></wowhead>