<?xml version="1.0" encoding="UTF-8"?><wowhead><item id="4565"><name><![CDATA[Simple Dagger]]></name><level>6</level><quality id="1">Common</quality><class id="2"><![CDATA[Weapons]]></class><subclass id="15"><![CDATA[Daggers]]></subclass><icon displayId="6433">inv_weapon_shortblade_01</icon><inventorySlot id="13">One-Hand</inventorySlot><htmlTooltip><![CDATA[<table><tr><td><!--nstart--><b class="q1">Simple Dagger</b><!--nend--><!--ndstart--><!--ndend--><span class="q"><br>Item Level <!--ilvl-->6</span><table width="100%"><tr><td>One-Hand</td><th><!--scstart2:15--><span class="q1">Dagger</span><!--scend--></th></tr></table><table width="100%"><tr>
    <td><span><!--dmg-->3 - 6 Damage</span></td>
    <th>Speed <!--spd-->1.80</th>
</tr></table><!--dps-->(2.50 damage per second)<!--ebstats--><!--egstats--><!--eistats--><!--e--><!--ps--><br>Durability 20 / 20</td></tr></table><table><tr><td><!--itemEffects:0--><div class="whtt-sellprice">Sell Price: <span class="moneycopper">38</span></div></td></tr></table>]]></htmlTooltip><json><![CDATA["classs":2,"displayid":6433,"dps":2.50,"flags2":8192,"id":4565,"level":6,"name":"Simple Dagger","quality":1,"slot":13,"slotbak":13,"source":[2,16],"speed":1.80,"subclass":15]]></json><jsonEquip><![CDATA["avgbuyout":4400,"displayid":6433,"dmgmax1":6,"dmgmin1":3,"dmgrange":1.00,"dmgtype1":0,"dps":2.50,"dura":20,"mledmgmax":6,"mledmgmin":3,"mledps":2.50,"mlespeed":1.80,"reqlevel":1,"sellprice":38,"sheathtype":3,"slotbak":13,"speed":1.80]]></jsonEquip><link>https://classic.wowhead.com/item=4565</link></item></wowhead>