<?xml version="1.0" encoding="UTF-8"?><wowhead><item id="13822"><name><![CDATA[Spiked Dagger]]></name><level>53</level><quality id="0">Poor</quality><class id="2"><![CDATA[Weapons]]></class><subclass id="15"><![CDATA[Daggers]]></subclass><icon displayId="4119">inv_weapon_shortblade_05</icon><inventorySlot id="13">One-Hand</inventorySlot><htmlTooltip><![CDATA[<table><tr><td><!--nstart--><b class="q0">Spiked Dagger</b><!--nend--><!--ndstart--><!--ndend--><span class="q"><br>Item Level <!--ilvl-->53</span><table width="100%"><tr><td>One-Hand</td><th><!--scstart2:15--><span class="q1">Dagger</span><!--scend--></th></tr></table><table width="100%"><tr>
    <td><span><!--dmg-->21 - 40 Damage</span></td>
    <th>Speed <!--spd-->1.60</th>
</tr></table><!--dps-->(19.06 damage per second)<!--ebstats--><!--egstats--><!--eistats--><!--e--><!--ps--><br>Durability 55 / 55</td></tr></table><table><tr><td>Requires Level <!--rlvl-->48<!--itemEffects:1--><div class="whtt-sellprice">Sell Price: <span class="moneygold">1</span> <span class="moneysilver">14</span> <span class="moneycopper">42</span></div></td></tr></table>]]></htmlTooltip><json><![CDATA["classs":2,"commondrop":true,"displayid":4119,"dps":19.06,"flags2":8192,"id":13822,"level":53,"name":"Spiked Dagger","quality":0,"reqlevel":48,"slot":13,"slotbak":13,"source":[2],"speed":1.60,"subclass":15]]></json><jsonEquip><![CDATA["avgbuyout":222,"displayid":4119,"dmgmax1":40,"dmgmin1":21,"dmgrange":1.00,"dmgtype1":0,"dps":19.06,"dura":55,"mledmgmax":40,"mledmgmin":21,"mledps":19.06,"mlespeed":1.60,"reqlevel":48,"sellprice":11442,"sheathtype":3,"slotbak":13,"speed":1.60]]></jsonEquip><link>https://classic.wowhead.com/item=13822</link></item></wowhead>