<?xml version="1.0" encoding="UTF-8"?><wowhead><item id="2271"><name><![CDATA[Staff of the Blessed Seer]]></name><level>23</level><quality id="3">Rare</quality><class id="2"><![CDATA[Weapons]]></class><subclass id="10"><![CDATA[Staves]]></subclass><icon displayId="20346">inv_staff_31</icon><inventorySlot id="17">Two-Hand</inventorySlot><htmlTooltip><![CDATA[<table><tr><td><!--nstart--><b class="q3">Staff of the Blessed Seer</b><!--nend--><!--ndstart--><!--ndend--><span class="q"><br>Item Level <!--ilvl-->23</span><br /><!--bo-->Binds when equipped<table width="100%"><tr><td>Two-Hand</td><th><!--scstart2:10--><span class="q1">Staff</span><!--scend--></th></tr></table><table width="100%"><tr>
    <td><span><!--dmg-->47 - 71 Damage</span></td>
    <th>Speed <!--spd-->3.00</th>
</tr></table><!--dps-->(19.67 damage per second)<br><span><!--stat7-->+2 Stamina</span><br><span><!--stat6-->+3 Spirit</span><!--ebstats--><!--egstats--><!--eistats--><!--e--><!--ps--><br>Durability 80 / 80</td></tr></table><table><tr><td>Requires Level <!--rlvl-->18<br><span class="q2">Equip: <a href="https://classic.wowhead.com/spell=9314" class="q2">Increases healing done by spells and effects by up to 24.</a></span><!--itemEffects:1--><div class="whtt-sellprice">Sell Price: <span class="moneysilver">32</span> <span class="moneycopper">55</span></div></td></tr></table>]]></htmlTooltip><json><![CDATA["classs":2,"displayid":20346,"dps":19.67,"flags2":8192,"id":2271,"level":23,"name":"Staff of the Blessed Seer","quality":3,"reqlevel":18,"slot":17,"slotbak":17,"source":[2],"sourcemore":[{"dd":-1,"z":719}],"speed":3.00,"subclass":10]]></json><jsonEquip><![CDATA["avgbuyout":250000,"displayid":20346,"dmgmax1":71,"dmgmin1":47,"dmgrange":1.00,"dmgtype1":0,"dps":19.67,"dura":80,"mledmgmax":71,"mledmgmin":47,"mledps":19.67,"mlespeed":3.00,"reqlevel":18,"sellprice":3255,"sheathtype":2,"slotbak":17,"speed":3.00,"spi":3,"splheal":24,"sta":2]]></jsonEquip><link>https://classic.wowhead.com/item=2271</link></item></wowhead>