[
    {
        "name": "Starfire Rank 1",
        "minDmg": 95,
        "maxDmg": 115,
        "magicSchool": 1,
        "type": "direct",
        "castTime": 3.5,
        "duration": 0,
        "manaCost": 95,
        "reqLvl": 20,
        "range": 30,
        "icon": "spell_arcane_starfire",
        "phase": 1
    },
    {
        "name": "Starfire Rank 2",
        "minDmg": 146,
        "maxDmg": 177,
        "magicSchool": 1,
        "type": "direct",
        "castTime": 3.5,
        "duration": 0,
        "manaCost": 135,
        "reqLvl": 26,
        "range": 30,
        "icon": "spell_arcane_starfire",
        "phase": 1
    },
    {
        "name": "Starfire Rank 3",
        "minDmg": 212,
        "maxDmg": 253,
        "magicSchool": 1,
        "type": "direct",
        "castTime": 3.5,
        "duration": 0,
        "manaCost": 180,
        "reqLvl": 34,
        "range": 30,
        "icon": "spell_arcane_starfire",
        "phase": 1
    },
    {
        "name": "Starfire Rank 4",
        "minDmg": 293,
        "maxDmg": 348,
        "magicSchool": 1,
        "type": "direct",
        "castTime": 3.5,
        "duration": 0,
        "manaCost": 230,
        "reqLvl": 42,
        "range": 30,
        "icon": "spell_arcane_starfire",
        "phase": 1
    },
    {
        "name": "Starfire Rank 5",
        "minDmg": 378,
        "maxDmg": 445,
        "magicSchool": 1,
        "type": "direct",
        "castTime": 3.5,
        "duration": 0,
        "manaCost": 275,
        "reqLvl": 50,
        "range": 30,
        "icon": "spell_arcane_starfire",
        "phase": 1
    },
    {
        "name": "Starfire Rank 6",
        "minDmg": 451,
        "maxDmg": 531,
        "magicSchool": 1,
        "type": "direct",
        "castTime": 3.5,
        "duration": 0,
        "manaCost": 315,
        "reqLvl": 58,
        "range": 30,
        "icon": "spell_arcane_starfire",
        "phase": 1
    },
    {
        "name": "Starfire Rank 7",
        "minDmg": 496,
        "maxDmg": 584,
        "magicSchool": 1,
        "type": "direct",
        "castTime": 3.5,
        "duration": 0,
        "manaCost": 340,
        "reqLvl": 60,
        "range": 30,
        "icon": "spell_arcane_starfire",
        "phase": 5
    },
    {
        "name": "Wrath Rank 1",
        "minDmg": 13,
        "maxDmg": 16,
        "magicSchool": 4,
        "type": "direct",
        "castTime": 1.5,
        "duration": 0,
        "manaCost": 20,
        "reqLvl": 1,
        "range": 30,
        "icon": "spell_nature_abolishmagic",
        "phase": 1
    },
    {
        "name": "Wrath Rank 2",
        "minDmg": 28,
        "maxDmg": 33,
        "magicSchool": 4,
        "type": "direct",
        "castTime": 1.7,
        "duration": 0,
        "manaCost": 35,
        "reqLvl": 6,
        "range": 30,
        "icon": "spell_nature_abolishmagic",
        "phase": 1
    },
    {
        "name": "Wrath Rank 3",
        "minDmg": 48,
        "maxDmg": 57,
        "magicSchool": 4,
        "type": "direct",
        "castTime": 2,
        "duration": 0,
        "manaCost": 55,
        "reqLvl": 14,
        "range": 30,
        "icon": "spell_nature_abolishmagic",
        "phase": 1
    },
    {
        "name": "Wrath Rank 4",
        "minDmg": 69,
        "maxDmg": 79,
        "magicSchool": 4,
        "type": "direct",
        "castTime": 2,
        "duration": 0,
        "manaCost": 70,
        "reqLvl": 22,
        "range": 30,
        "icon": "spell_nature_abolishmagic",
        "phase": 1
    },
    {
        "name": "Wrath Rank 5",
        "minDmg": 108,
        "maxDmg": 123,
        "magicSchool": 4,
        "type": "direct",
        "castTime": 2,
        "duration": 0,
        "manaCost": 100,
        "reqLvl": 30,
        "range": 30,
        "icon": "spell_nature_abolishmagic",
        "phase": 1
    },
    {
        "name": "Wrath Rank 6",
        "minDmg": 148,
        "maxDmg": 167,
        "magicSchool": 4,
        "type": "direct",
        "castTime": 2,
        "duration": 0,
        "manaCost": 125,
        "reqLvl": 38,
        "range": 30,
        "icon": "spell_nature_abolishmagic",
        "phase": 1
    },
    {
        "name": "Wrath Rank 7",
        "minDmg": 198,
        "maxDmg": 221,
        "magicSchool": 4,
        "type": "direct",
        "castTime": 2,
        "duration": 0,
        "manaCost": 155,
        "reqLvl": 46,
        "range": 30,
        "icon": "spell_nature_abolishmagic",
        "phase": 1
    },
    {
        "name": "Wrath Rank 8",
        "minDmg": 248,
        "maxDmg": 277,
        "magicSchool": 4,
        "type": "direct",
        "castTime": 2,
        "duration": 0,
        "manaCost": 180,
        "reqLvl": 54,
        "range": 30,
        "icon": "spell_nature_abolishmagic",
        "phase": 1
    },
    {
        "name": "Moonfire Rank 1",
        "minDmg": 9,
        "maxDmg": 12,
        "magicSchool": 1,
        "type": "hybrid",
        "castTime": 0,
        "tickDmg": 4,
        "tickRate": 3,
        "duration": 9,
        "manaCost": 25,
        "reqLvl": 4,
        "range": 30,
        "icon": "spell_nature_starfall",
        "phase": 1
    },
    {
        "name": "Moonfire Rank 2",
        "minDmg": 17,
        "maxDmg": 21,
        "magicSchool": 1,
        "type": "hybrid",
        "castTime": 0,
        "duration": 12,
        "tickDmg": 8,
        "tickRate": 3,
        "manaCost": 50,
        "reqLvl": 10,
        "range": 30,
        "icon": "spell_nature_starfall",
        "phase": 1
    },
    {
        "name": "Moonfire Rank 3",
        "minDmg": 30,
        "maxDmg": 37,
        "magicSchool": 1,
        "type": "hybrid",
        "castTime": 0,
        "duration": 12,
        "tickDmg": 13,
        "tickRate": 3,
        "manaCost": 75,
        "reqLvl": 16,
        "range": 30,
        "icon": "spell_nature_starfall",
        "phase": 1
    },
    {
        "name": "Moonfire Rank 4",
        "minDmg": 47,
        "maxDmg": 55,
        "magicSchool": 1,
        "type": "hybrid",
        "castTime": 0,
        "duration": 12,
        "tickDmg": 20,
        "tickRate": 3,
        "manaCost": 105,
        "reqLvl": 22,
        "range": 30,
        "icon": "spell_nature_starfall",
        "phase": 1
    },
    {
        "name": "Moonfire Rank 5",
        "minDmg": 70,
        "maxDmg": 82,
        "magicSchool": 1,
        "type": "hybrid",
        "castTime": 0,
        "duration": 12,
        "tickDmg": 31,
        "tickRate": 3,
        "manaCost": 150,
        "reqLvl": 28,
        "range": 30,
        "icon": "spell_nature_starfall",
        "phase": 1
    },
    {
        "name": "Moonfire Rank 6",
        "minDmg": 91,
        "maxDmg": 108,
        "magicSchool": 1,
        "type": "hybrid",
        "castTime": 0,
        "duration": 12,
        "tickDmg": 41,
        "tickRate": 3,
        "manaCost": 190,
        "reqLvl": 34,
        "range": 30,
        "icon": "spell_nature_starfall",
        "phase": 1
    },
    {
        "name": "Moonfire Rank 7",
        "minDmg": 117,
        "maxDmg": 137,
        "magicSchool": 1,
        "type": "hybrid",
        "castTime": 0,
        "duration": 12,
        "tickDmg": 53,
        "tickRate": 3,
        "manaCost": 235,
        "reqLvl": 40,
        "range": 30,
        "icon": "spell_nature_starfall",
        "phase": 1
    },
    {
        "name": "Moonfire Rank 8",
        "minDmg": 143,
        "maxDmg": 168,
        "magicSchool": 1,
        "type": "hybrid",
        "castTime": 0,
        "duration": 12,
        "tickDmg": 66,
        "tickRate": 3,
        "manaCost": 280,
        "reqLvl": 46,
        "range": 30,
        "icon": "spell_nature_starfall",
        "phase": 1
    },
    {
        "name": "Moonfire Rank 9",
        "minDmg": 172,
        "maxDmg": 200,
        "magicSchool": 1,
        "type": "hybrid",
        "castTime": 0,
        "duration": 12,
        "tickDmg": 80,
        "tickRate": 3,
        "manaCost": 325,
        "reqLvl": 52,
        "range": 30,
        "icon": "spell_nature_starfall",
        "phase": 1
    },
    {
        "name": "Moonfire Rank 10",
        "minDmg": 195,
        "maxDmg": 228,
        "magicSchool": 1,
        "type": "hybrid",
        "castTime": 0,
        "duration": 12,
        "tickDmg": 96,
        "tickRate": 3,
        "manaCost": 375,
        "reqLvl": 58,
        "range": 30,
        "icon": "spell_nature_starfall",
        "phase": 1
    },
    {
        "name": "Insect Swarm Rank 1",
        "magicSchool": 4,
        "type": "periodic",
        "castTime": 0,
        "tickDmg": 11,
        "tickRate": 2,
        "duration": 12,
        "manaCost": 45,
        "reqLvl": 20,
        "range": 30,
        "phase": 1,
        "icon": "spell_nature_insectswarm",
        "secondary": "cth-2"
    },
    {
        "name": "Insect Swarm Rank 2",
        "magicSchool": 4,
        "type": "periodic",
        "castTime": 0,
        "tickDmg": 23,
        "duration": 12,
        "tickRate": 3,
        "manaCost": 85,
        "reqLvl": 30,
        "range": 30,
        "phase": 1,
        "icon": "spell_nature_insectswarm",
        "secondary": "cth-2"
    },
    {
        "name": "Insect Swarm Rank 3",
        "magicSchool": 4,
        "type": "periodic",
        "castTime": 0,
        "duration": 12,
        "tickDmg": 29,
        "tickRate": 2,
        "manaCost": 100,
        "reqLvl": 40,
        "range": 30,
        "phase": 1,
        "icon": "spell_nature_insectswarm",
        "secondary": "cth-2"
    },
    {
        "name": "Insect Swarm Rank 4",
        "magicSchool": 4,
        "type": "periodic",
        "castTime": 0,
        "duration": 12,
        "tickDmg": 44,
        "tickRate": 3,
        "manaCost": 140,
        "reqLvl": 50,
        "range": 30,
        "phase": 1,
        "icon": "spell_nature_insectswarm",
        "secondary": "cth-2"
    },
    {
        "name": "Insect Swarm Rank 5",
        "magicSchool": 4,
        "type": "periodic",
        "castTime": 0,
        "duration": 12,
        "tickDmg": 54,
        "tickRate": 2,
        "manaCost": 160,
        "reqLvl": 60,
        "range": 30,
        "phase": 1,
        "icon": "spell_nature_insectswarm",
        "secondary": "cth-2"
    },
    {
        "name": "Hurricane Rank 1",
        "magicSchool": 4,
        "type": "periodic",
        "castTime": 0,
        "duration": 10,
        "tickDmg": 72,
        "tickRate": 1,
        "manaCost": 880,
        "reqLvl": 40,
        "range": 30,
        "phase": 1,
        "icon": "spell_nature_cyclone",
        "secondary": "haste-25"
    },
    {
        "name": "Hurricane Rank 2",
        "magicSchool": 4,
        "type": "periodic",
        "castTime": 0,
        "duration": 10,
        "tickDmg": 102,
        "tickRate": 1,
        "manaCost": 1180,
        "reqLvl": 50,
        "range": 30,
        "phase": 1,
        "icon": "spell_nature_cyclone",
        "secondary": "haste-25"
    },
    {
        "name": "Hurricane Rank 3",
        "magicSchool": 4,
        "type": "periodic",
        "castTime": 0,
        "duration": 10,
        "tickDmg": 134,
        "tickRate": 1,
        "manaCost": 1495,
        "reqLvl": 60,
        "range": 30,
        "phase": 1,
        "icon": "spell_nature_cyclone",
        "secondary": "haste-25"
    }
]